mo_json/__init__.py
mo_json/array.py
mo_json/decoder.py
mo_json/encoder.py
mo_json/scrubber.py
mo_json/stream.py
mo_json/typed_encoder.py
mo_json/typed_object.py
mo_json/types.py
mo_json/utils.py
mo_json-6.686.25166.dist-info/licenses/LICENSE
mo_json-6.686.25166.dist-info/METADATA
mo_json-6.686.25166.dist-info/WHEEL
mo_json-6.686.25166.dist-info/top_level.txt
mo_json-6.686.25166.dist-info/RECORD
