Metadata-Version: 2.4
Name: mo-json
Version: 6.686.25166
Summary: More JSON Tools! 
Home-page: https://github.com/klahnakoski/mo-json
Author: Kyle Lahnakoski
Author-email: kyle@lahnakoski.com
License: MPL 2.0
Classifier: Development Status :: 4 - Beta
Classifier: License :: OSI Approved :: Mozilla Public License 2.0 (MPL 2.0)
Classifier: Programming Language :: Python :: 3.8
Classifier: Programming Language :: Python :: 3.9
Classifier: Topic :: Software Development :: Libraries
Classifier: Topic :: Software Development :: Libraries :: Python Modules
Classifier: Programming Language :: Python :: 3.10
Classifier: Programming Language :: Python :: 3.11
Classifier: Programming Language :: Python :: 3.12
Classifier: Programming Language :: Python :: 3.13
License-File: LICENSE
Requires-Dist: hjson
Requires-Dist: mo-dots==10.685.25166
Requires-Dist: mo-future==7.685.25166
Requires-Dist: mo-logs==8.685.25166
Requires-Dist: mo-times==5.685.25166
Provides-Extra: tests
Requires-Dist: mo-testing>=8.674.25037; extra == "tests"
Requires-Dist: mo-threads>=6.681.25075; extra == "tests"
Requires-Dist: pytz>=2025.2; extra == "tests"
Requires-Dist: beautifulsoup4>=4.13.3; extra == "tests"
Dynamic: author
Dynamic: author-email
Dynamic: classifier
Dynamic: description
Dynamic: description-content-type
Dynamic: home-page
Dynamic: license
Dynamic: license-file
Dynamic: provides-extra
Dynamic: requires-dist
Dynamic: summary
